autorml/__init__.py
autorml/__main__.py
autorml/logical_source.py
autorml/mapping_synthesis.py
autorml/materialize.py
autorml/predicate_object_map.py
autorml/subject_map.py
autorml/term_maps.py
autorml/annotation/load_annotations.py
autorml/annotation/mtab.py
autorml/annotation/save_annotations.py
autorml/annotation/torchic_tab.py
autorml-0.1.6.dist-info/LICENSE
autorml-0.1.6.dist-info/METADATA
autorml-0.1.6.dist-info/WHEEL
autorml-0.1.6.dist-info/top_level.txt
autorml-0.1.6.dist-info/RECORD
