Metadata-Version: 2.1
Name: autorml
Version: 0.1.6
Summary: AutoRML: A framework for automatic RML mapping generation using semantic table annotations
Home-page: https://github.com/dtai-kg/AutoRML
Author: Ioannis Dasoulas
Author-email: ioannis.dasoulas@kuleuven.be
License: Apache-2.0
Classifier: Programming Language :: Python :: 3
Classifier: License :: OSI Approved :: Apache Software License
Classifier: Intended Audience :: Developers
Classifier: Intended Audience :: Science/Research
Classifier: Natural Language :: English
Requires-Python: >=3.9, <3.12
License-File: LICENSE
Requires-Dist: yatter ==1.1.4
Requires-Dist: morph-kgc ==2.8.0
Requires-Dist: requests ==2.32.2
Requires-Dist: pandas ==2.2.1
Requires-Dist: pyyaml ==6.0.2
Requires-Dist: torchic-tab-heuristic ==0.1.2
